LICENSE
README.md
setup.cfg
setup.py
mintapi/__init__.py
mintapi/__main__.py
mintapi/api.py
mintapi/browser.py
mintapi/cli.py
mintapi/constants.py
mintapi/endpoints.py
mintapi/exceptions.py
mintapi/filters.py
mintapi/rest.py
mintapi/signIn.py
mintapi/transactions.py
mintapi/trends.py
mintapi.egg-info/PKG-INFO
mintapi.egg-info/SOURCES.txt
mintapi.egg-info/dependency_links.txt
mintapi.egg-info/entry_points.txt
mintapi.egg-info/requires.txt
mintapi.egg-info/top_level.txt