Metadata-Version: 2.1
Name: mintapi
Version: 2.13
Summary: a screen-scraping API for Mint.com
Home-page: https://github.com/mintapi/mintapi
Author: Michael Rooney
Author-email: mrooney.mintapi@rowk.com
License: The MIT License
Platform: UNKNOWN
Requires-Python: >=3.6
License-File: LICENSE
